tet_raven/__init__.py
tet_raven/javascript.py
tet_raven-0.1.dist-info/DESCRIPTION.rst
tet_raven-0.1.dist-info/METADATA
tet_raven-0.1.dist-info/RECORD
tet_raven-0.1.dist-info/WHEEL
tet_raven-0.1.dist-info/metadata.json
tet_raven-0.1.dist-info/top_level.txt
